python_markdown_slack/__init__.py
python_markdown_slack/list_handler.py
python_markdown_slack-1.0.6.dist-info/LICENSE
python_markdown_slack-1.0.6.dist-info/METADATA
python_markdown_slack-1.0.6.dist-info/WHEEL
python_markdown_slack-1.0.6.dist-info/top_level.txt
python_markdown_slack-1.0.6.dist-info/RECORD
