Metadata-Version: 2.1
Name: python-markdown-slack
Version: 1.0.6
Summary: UNKNOWN
Home-page: UNKNOWN
Author: UNKNOWN
Author-email: UNKNOWN
License: MIT
Platform: UNKNOWN
Requires-Dist: markdown (==2.6.6)
